jbeval/__init__.py
jbeval/interface.py
jbeval/processing.py
jbeval-0.0.0.dist-info/LICENSE
jbeval-0.0.0.dist-info/METADATA
jbeval-0.0.0.dist-info/WHEEL
jbeval-0.0.0.dist-info/top_level.txt
jbeval-0.0.0.dist-info/RECORD
